.bumpversion.cfg
CONTRIBUTING.md
LICENSE
MANIFEST.in
Makefile
README.md
pyproject.toml
setup.py
zkpy/__init__.py
zkpy/circuit.py
zkpy/ptau.py
zkpy/utils.py
zkpy.egg-info/PKG-INFO
zkpy.egg-info/SOURCES.txt
zkpy.egg-info/dependency_links.txt
zkpy.egg-info/requires.txt
zkpy.egg-info/top_level.txt
zkpy/example_circuits/circom.circom
zkpy/example_circuits/input.json
zkpy/tests/test_circuit.py
zkpy/tests/test_integrations.py
zkpy/tests/test_ptau.py
zkpy/tests/test_circuit/example_circuit.circom
zkpy/tests/test_circuit/example_circuit.r1cs
zkpy/tests/test_circuit/example_circuit.sym
zkpy/tests/test_circuit/input.json
zkpy/tests/test_circuit/phase2.ptau
zkpy/tests/test_circuit/proof.json
zkpy/tests/test_circuit/public.json
zkpy/tests/test_circuit/vkey.json
zkpy/tests/test_circuit/witness.wtns
zkpy/tests/test_circuit/zkey.zkey
zkpy/tests/test_circuit/zkey_groth16.zkey
zkpy/tests/test_circuit/example_circuit_js/example_circuit.wasm
zkpy/tests/test_circuit/example_circuit_js/generate_witness.js
zkpy/tests/test_circuit/example_circuit_js/witness_calculator.js
zkpy/tests/test_ptau/beaconed.ptau
zkpy/tests/test_ptau/challenge
zkpy/tests/test_ptau/contributed.ptau
zkpy/tests/test_ptau/phase2.ptau
zkpy/tests/test_ptau/response
zkpy/tests/test_ptau/start.ptau