Metadata-Version: 2.1
Name: zkpy
Version: 0.2.0
Summary: A Python library that allows for easy compiling/proving/verifying of zk circuits
Author-email: Sahil Mahendrakar <sahil.mahendrakar@gmail.com>
License:                                  Apache License
Project-URL: repository, https://github.com/sahilmahendrakar/zkpy
Classifier: Development Status :: 2 - Pre-Alpha
Classifier: Programming Language :: Python :: Implementation :: CPython
Classifier: Programming Language :: Python :: Implementation :: PyPy
Classifier: Programming Language :: Python :: 3
Classifier: Programming Language :: Python :: 3.7
Classifier: Programming Language :: Python :: 3.8
Classifier: Programming Language :: Python :: 3.9
Classifier: Programming Language :: Python :: 3.10
Classifier: Programming Language :: Python :: 3.11
Requires-Python: >=3.7
Provides-Extra: develop
License-File: LICENSE
